docker_ps_traefik.py
docker_ps_traefik-0.2.1.dist-info/entry_points.txt
docker_ps_traefik-0.2.1.dist-info/LICENSE
docker_ps_traefik-0.2.1.dist-info/WHEEL
docker_ps_traefik-0.2.1.dist-info/METADATA
docker_ps_traefik-0.2.1.dist-info/RECORD
